okcompute/__init__.py
okcompute/okc.py
okcompute/okc_html_reports.py
okcompute/version.py
okcompute-1.0.1.dist-info/METADATA
okcompute-1.0.1.dist-info/RECORD
okcompute-1.0.1.dist-info/WHEEL
okcompute-1.0.1.dist-info/top_level.txt
