Metadata-Version: 2.1
Name: okcompute
Version: 1.0.1
Summary: Fault tolerant analysis framework.
Home-page: https://github.com/swift-nav/okcompute
Author: Swift Navigation
Author-email: dev@swiftnav.com
Maintainer: Swift Navigation
Maintainer-email: dev@swiftnav.com
License: MIT
Project-URL: Documentation, http://okcompute.swiftnav.com/
Project-URL: Code, https://github.com/swift-nav/okcompute
Project-URL: Issue tracker, https://github.com/swift-nav/okcompute/issues
Platform: UNKNOWN
Classifier: Development Status :: 4 - Beta
Classifier: Intended Audience :: Developers
Classifier: Programming Language :: Python
Classifier: Programming Language :: Python :: 2
Classifier: Programming Language :: Python :: 3
Classifier: Programming Language :: Python :: 2.7
Classifier: Programming Language :: Python :: 3.6
Classifier: Topic :: Software Development
Provides-Extra: plot
Provides-Extra: appdoc
Provides-Extra: doc
Requires-Dist: networkx
Provides-Extra: appdoc
Requires-Dist: pygraphviz; extra == 'appdoc'
Requires-Dist: jinja2; extra == 'appdoc'
Provides-Extra: doc
Requires-Dist: sphinx; extra == 'doc'
Provides-Extra: plot
Requires-Dist: pygraphviz; extra == 'plot'
